.coveragerc
.gitlab-ci.yml
CHANGES.rst
CONTRIBUTORS.rst
DEVELOP.rst
LICENSE.GPL
LICENSE.rst
MANIFEST.in
README.rst
base.cfg
bobtemplate.cfg
buildout.cfg
constraints.txt
constraints_plone52.txt
constraints_plone60.txt
dependabot.yml
pyproject.toml
requirements.txt
requirements_plone52.txt
requirements_plone60.txt
setup.cfg
setup.py
test_plone52.cfg
test_plone60.cfg
src/collective/__init__.py
src/collective.contentrules.telegram.egg-info/PKG-INFO
src/collective.contentrules.telegram.egg-info/SOURCES.txt
src/collective.contentrules.telegram.egg-info/dependency_links.txt
src/collective.contentrules.telegram.egg-info/entry_points.txt
src/collective.contentrules.telegram.egg-info/namespace_packages.txt
src/collective.contentrules.telegram.egg-info/not-zip-safe
src/collective.contentrules.telegram.egg-info/requires.txt
src/collective.contentrules.telegram.egg-info/top_level.txt
src/collective/contentrules/__init__.py
src/collective/contentrules/telegram/__init__.py
src/collective/contentrules/telegram/action.py
src/collective/contentrules/telegram/action.zcml
src/collective/contentrules/telegram/configure.zcml
src/collective/contentrules/telegram/interfaces.py
src/collective/contentrules/telegram/permissions.zcml
src/collective/contentrules/telegram/setuphandlers.py
src/collective/contentrules/telegram/telegram.pt
src/collective/contentrules/telegram/testing.py
src/collective/contentrules/telegram/controlpanels/__init__.py
src/collective/contentrules/telegram/controlpanels/configure.zcml
src/collective/contentrules/telegram/controlpanels/telegram_bot_configuration_control_panel/__init__.py
src/collective/contentrules/telegram/controlpanels/telegram_bot_configuration_control_panel/configure.zcml
src/collective/contentrules/telegram/controlpanels/telegram_bot_configuration_control_panel/controlpanel.py
src/collective/contentrules/telegram/locales/README.rst
src/collective/contentrules/telegram/locales/__init__.py
src/collective/contentrules/telegram/locales/collective.contentrules.telegram.pot
src/collective/contentrules/telegram/locales/update.py
src/collective/contentrules/telegram/locales/update.sh
src/collective/contentrules/telegram/locales/en/LC_MESSAGES/collective.contentrules.telegram.po
src/collective/contentrules/telegram/profiles/default/browserlayer.xml
src/collective/contentrules/telegram/profiles/default/catalog.xml
src/collective/contentrules/telegram/profiles/default/controlpanel.xml
